icosalattice/Adjacency.py
icosalattice/BoxCornerMapping.py
icosalattice/ConstantMakerDecorator.py
icosalattice/Edges.py
icosalattice/Faces.py
icosalattice/IcosahedronMath.py
icosalattice/MapCoordinateMath.py
icosalattice/ParentsAndChildren.py
icosalattice/PlotAdjacency.py
icosalattice/PointCodeArithmetic.py
icosalattice/StartingPoints.py
icosalattice/UnitSpherePoint.py
icosalattice/__init__.py
icosalattice-0.0.4.dist-info/LICENSE
icosalattice-0.0.4.dist-info/METADATA
icosalattice-0.0.4.dist-info/WHEEL
icosalattice-0.0.4.dist-info/top_level.txt
icosalattice-0.0.4.dist-info/RECORD
