Metadata-Version: 2.1
Name: icosalattice
Version: 0.0.4
Summary: An icosahedron-based lattice for the 2-sphere
Author: Wesley Kuhron Jones
Project-URL: Homepage, https://github.com/Kuhron/icosalattice
Project-URL: Issues, https://github.com/Kuhron/icosalattice/issues
Classifier: Programming Language :: Python :: 3
Classifier: License :: OSI Approved :: GNU Affero General Public License v3
Classifier: Operating System :: OS Independent
Requires-Python: >=3.8
License-File: LICENSE
